PipLab/__init__.py
PipLab/test.py
SemLabExam-0.0.5.dist-info/LICENSE.txt
SemLabExam-0.0.5.dist-info/METADATA
SemLabExam-0.0.5.dist-info/WHEEL
SemLabExam-0.0.5.dist-info/top_level.txt
SemLabExam-0.0.5.dist-info/RECORD
