Metadata-Version: 2.1
Name: SemLabExam
Version: 0.0.5
Summary: Lab Exam
Home-page: UNKNOWN
Author: skriller
Author-email: <subhashguptap.ai21@rvce.edu.in>
License: UNKNOWN
Keywords: python,video,stream,video stream,camera stream,sockets
Platform: UNKNOWN
Classifier: Development Status :: 1 - Planning
Classifier: Intended Audience :: Developers
Classifier: Programming Language :: Python :: 3
Classifier: Operating System :: Unix
Classifier: Operating System :: MacOS :: MacOS X
Classifier: Operating System :: Microsoft :: Windows
License-File: LICENSE.txt
